labelvis/__init__.py
labelvis/config.py
labelvis/dataloaders.py
labelvis/labelvis.py
labelvis/utils.py
labelvis-0.1.0.dist-info/LICENSE
labelvis-0.1.0.dist-info/METADATA
labelvis-0.1.0.dist-info/WHEEL
labelvis-0.1.0.dist-info/top_level.txt
labelvis-0.1.0.dist-info/RECORD
