Metadata-Version: 2.1
Name: labelvis
Version: 0.1.0
Summary: python library to visualize object detection labels
Home-page: https://github.com/satheeshkatipomu/labelvis
Author: Satheesh Katipomu
License: UNKNOWN
Platform: linux
Platform: unix
Classifier: Development Status :: 4 - Beta
Classifier: Intended Audience :: Developers
Classifier: Topic :: Utilities
Classifier: Programming Language :: Python :: 3.7
Classifier: Programming Language :: Python :: 3.8
Classifier: Programming Language :: Python :: 3 :: Only
Requires-Python: >=3.7
Requires-Dist: numpy (==1.20.1)
Requires-Dist: pillow (==8.1.2)
Requires-Dist: pycocotools (==2.0.2)
Requires-Dist: joblib (==1.0.1)
Requires-Dist: matplotlib (==3.3.4)
Requires-Dist: bounding-box (==0.1.3)
